xyz_mytraining/__init__.py
xyz_mytraining/apis.py
xyz_mytraining/apps.py
xyz_mytraining/choices.py
xyz_mytraining/models.py
xyz_mytraining/serializers.py
xyz_mytraining/migrations/0001_initial.py
xyz_mytraining/migrations/0002_auto_20200719_1136.py
xyz_mytraining/migrations/0003_auto_20200724_0540.py
xyz_mytraining/migrations/__init__.py
xyz_mytraining-0.1.0.dist-info/DESCRIPTION.rst
xyz_mytraining-0.1.0.dist-info/METADATA
xyz_mytraining-0.1.0.dist-info/RECORD
xyz_mytraining-0.1.0.dist-info/WHEEL
xyz_mytraining-0.1.0.dist-info/metadata.json
xyz_mytraining-0.1.0.dist-info/top_level.txt
